django_expvar-0.2.1.dist-info/DESCRIPTION.rst
django_expvar-0.2.1.dist-info/METADATA
django_expvar-0.2.1.dist-info/RECORD
django_expvar-0.2.1.dist-info/WHEEL
django_expvar-0.2.1.dist-info/metadata.json
django_expvar-0.2.1.dist-info/top_level.txt
expvar/__init__.py
expvar/__init__.pyc
expvar/models.py
expvar/models.pyc
expvar/views.py
expvar/views.pyc
