Metadata-Version: 2.0
Name: django-expvar
Version: 0.2.1
Summary: Django expvar endpoint
Home-page: https://github.com/thraxil/django-expvar
Author: Anders Pearson
Author-email: anders@columbia.edu
License: BSD
Platform: any
Requires-Dist: Django (>=1.8)
Requires-Dist: nose
Requires-Dist: six
